
main <sample.lua:0,0> (50 instructions, 200 bytes at 007E7D38)
0+ params, 7 slots, 0 upvalues, 9 locals, 8 constants, 1 function
	1	[1]	LOADK    	0 -1	; 1
	2	[1]	LOADK    	1 -3	; "the quick brown fox\r\n"
	3	[1]	SETGLOBAL	1 -2	; b
	4	[2]	CLOSURE  	1 0	; 0031ED38
	5	[2]	MOVE     	0 0
	6	[2]	SETGLOBAL	1 -4	; c
	7	[3]	LOADNIL  	1 1
	8	[3]	SETGLOBAL	1 -4	; c
	9	[3]	UNM      	1 0
	10	[3]	SETGLOBAL	1 -4	; c
	11	[3]	GETGLOBAL	1 -2	; b
	12	[3]	NOT      	1 1
	13	[3]	SETGLOBAL	1 -4	; c
	14	[4]	LOADK    	1 -1	; 1
	15	[4]	LOADK    	2 -5	; 10
	16	[4]	LOADK    	3 -1	; 1
	17	[4]	FORPREP  	1 3	; to 21
	18	[4]	ADD      	0 0 -6	; - 2
	19	[4]	GETGLOBAL	5 -4	; c
	20	[4]	CALL     	5 1 1
	21	[4]	FORLOOP  	1 -4	; to 18
	22	[5]	NEWTABLE 	1 0 0
	23	[5]	MOVE     	0 1
	24	[5]	SETTABLE 	0 -1 -7	; 1 false
	25	[5]	GETTABLE 	1 0 -1	; 1
	26	[5]	SETGLOBAL	1 -2	; b
	27	[6]	GETGLOBAL	1 -8	; d
	28	[6]	GETGLOBAL	2 -4	; c
	29	[6]	GETGLOBAL	3 -2	; b
	30	[6]	CONCAT   	0 1 3
	31	[6]	GETGLOBAL	1 -2	; b
	32	[6]	GETGLOBAL	2 -4	; c
	33	[6]	EQ       	1 1 2
	34	[6]	JMP      	1	; to 36
	35	[6]	LOADBOOL 	0 0 1
	36	[6]	LOADBOOL 	0 1 0
	37	[6]	NEWTABLE 	1 2 0
	38	[6]	LOADK    	2 -1	; 1
	39	[6]	LOADK    	3 -6	; 2
	40	[6]	SETLIST  	1 2 1	; 1
	41	[6]	MOVE     	0 1
	42	[7]	GETGLOBAL	1 -2	; b
	43	[7]	CALL     	1 1 4
	44	[7]	JMP      	2	; to 47
	45	[7]	LOADK    	5 -1	; 1
	46	[7]	SETGLOBAL	5 -2	; b
	47	[7]	TFORLOOP 	1 1
	48	[7]	JMP      	-4	; to 45
	49	[8]	RETURN   	0 1
	50	[8]	RETURN   	0 1

function <sample.lua:2,2> (5 instructions, 20 bytes at 0031ED38)
0 params, 2 slots, 1 upvalue, 0 locals, 1 constant, 0 functions
	1	[2]	GETUPVAL 	0 0	; a
	2	[2]	SETGLOBAL	0 -1	; b
	3	[2]	GETGLOBAL	0 -1	; b
	4	[2]	SETUPVAL 	0 0	; a
	5	[2]	RETURN   	0 1
